edtools/__init__.py
edtools/atomlib.yaml
edtools/autoindex.py
edtools/cif_tools.py
edtools/cluster.py
edtools/extract_xds_info.py
edtools/find_beam_center.py
edtools/find_cell.py
edtools/find_rotation_axis.py
edtools/make_shelx.py
edtools/make_xscale.py
edtools/period_table.py
edtools/reflection_tool.py
edtools/run_pointless.py
edtools/scattering_factor.py
edtools/spglib.yaml
edtools/update_xds.py
edtools/utils.py
edtools/widgets.py
edtools/wsl.py
edtools/instrument/Lab6.cif
edtools/instrument/Themis-Z.cif
edtools-1.1.1.dist-info/licenses/LICENCE
edtools-1.1.1.dist-info/METADATA
edtools-1.1.1.dist-info/WHEEL
edtools-1.1.1.dist-info/entry_points.txt
edtools-1.1.1.dist-info/top_level.txt
edtools-1.1.1.dist-info/RECORD
