Metadata-Version: 2.4
Name: edtools
Version: 1.1.1
Summary: Collection of tools for automated processing and clustering of electron diffraction data.
Author-email: Stef Smeets <s.smeets@esciencecenter.nl>
License-Expression: BSD-3-Clause
Project-URL: homepage, http://github.com/instamatic-dev/edtools
Project-URL: issues, http://github.com/instamatic-dev/edtools/issues
Project-URL: documentation, http://github.com/instamatic-dev/edtools
Project-URL: changelog, http://github.com/instamatic-dev/edtools/releases
Keywords: electron-diffraction,microed,xds,pipeline,cluster-analysis
Classifier: Development Status :: 5 - Production/Stable
Classifier: Intended Audience :: Science/Research
Classifier: Natural Language :: English
Classifier: Programming Language :: Python :: 3
Classifier: Programming Language :: Python :: 3.8
Classifier: Programming Language :: Python :: 3.9
Classifier: Programming Language :: Python :: 3.10
Classifier: Programming Language :: Python :: 3.11
Classifier: Programming Language :: Python :: 3.12
Classifier: Programming Language :: Python :: 3.13
Classifier: Topic :: Scientific/Engineering
Requires-Python: >=3.8
License-File: LICENCE
Requires-Dist: numpy>=1.18.2
Requires-Dist: matplotlib>=3.2.1
Requires-Dist: scipy>=1.4.1
Requires-Dist: pandas>=1.0.3
Requires-Dist: uncertainties>=3.1.2
Requires-Dist: PyYAML>=5.4.1
Requires-Dist: openpyxl>=3.0.10
Provides-Extra: develop
Requires-Dist: check-manifest; extra == "develop"
Requires-Dist: pre-commit; extra == "develop"
Requires-Dist: bump-my-version; extra == "develop"
Provides-Extra: publish
Requires-Dist: twine; extra == "publish"
Requires-Dist: wheel; extra == "publish"
Requires-Dist: build; extra == "publish"
Dynamic: license-file
